jupyter_library/__init__.py
jupyter_library/_version.py
jupyter_library/handlers.py
jupyter_library/tests/__init__.py
jupyter_library/tests/test_handlers.py
jupyter_library-0.0.2.data/data/etc/jupyter/jupyter_notebook_config.d/jupyter_library.json
jupyter_library-0.0.2.data/data/etc/jupyter/jupyter_server_config.d/jupyter_library.json
jupyter_library-0.0.2.data/data/share/jupyter/labextensions/@datalayer/jupyter-library/build_log.json
jupyter_library-0.0.2.data/data/share/jupyter/labextensions/@datalayer/jupyter-library/package.json
jupyter_library-0.0.2.data/data/share/jupyter/labextensions/@datalayer/jupyter-library/schemas/@datalayer/jupyter-library/package.json.orig
jupyter_library-0.0.2.data/data/share/jupyter/labextensions/@datalayer/jupyter-library/schemas/@datalayer/jupyter-library/plugin.json
jupyter_library-0.0.2.data/data/share/jupyter/labextensions/@datalayer/jupyter-library/static/design_icons_lib_index_js.1dd4281a474d32f296b4.js
jupyter_library-0.0.2.data/data/share/jupyter/labextensions/@datalayer/jupyter-library/static/design_icons_lib_index_js.1dd4281a474d32f296b4.js.map
jupyter_library-0.0.2.data/data/share/jupyter/labextensions/@datalayer/jupyter-library/static/lib_index_js.27ebf0c8a13c9ca0cfc6.js
jupyter_library-0.0.2.data/data/share/jupyter/labextensions/@datalayer/jupyter-library/static/lib_index_js.27ebf0c8a13c9ca0cfc6.js.map
jupyter_library-0.0.2.data/data/share/jupyter/labextensions/@datalayer/jupyter-library/static/node_modules_object-assign_index_js.3261c70da90b87044144.js
jupyter_library-0.0.2.data/data/share/jupyter/labextensions/@datalayer/jupyter-library/static/node_modules_object-assign_index_js.3261c70da90b87044144.js.map
jupyter_library-0.0.2.data/data/share/jupyter/labextensions/@datalayer/jupyter-library/static/remoteEntry.9cef32882d228dbbfbe8.js
jupyter_library-0.0.2.data/data/share/jupyter/labextensions/@datalayer/jupyter-library/static/remoteEntry.9cef32882d228dbbfbe8.js.map
jupyter_library-0.0.2.dist-info/METADATA
jupyter_library-0.0.2.dist-info/WHEEL
jupyter_library-0.0.2.dist-info/licenses/LICENSE
jupyter_library-0.0.2.dist-info/RECORD
